lushalytics/__init__.py
lushalytics/plotting/CategoricalBarPlot.py
lushalytics/plotting/DatePlotingClasses.py
lushalytics/plotting/DatePlottingSuper.py
lushalytics/plotting/__init__.py
lushalytics/streamlit_comps/Multiselect.py
lushalytics/streamlit_comps/__init__.py
lushalytics/utils/__init__.py
lushalytics/utils/helper_funcs.py
lushalytics-1.4.91.dist-info/METADATA
lushalytics-1.4.91.dist-info/WHEEL
lushalytics-1.4.91.dist-info/top_level.txt
lushalytics-1.4.91.dist-info/RECORD
