Metadata-Version: 2.1
Name: lushalytics
Version: 1.4.91
Summary: tools for quick and convenient data analysis
Home-page: UNKNOWN
Author: Moran Reznik
License: UNKNOWN
Platform: UNKNOWN
Requires-Dist: pandas
Requires-Dist: plotly
